aflowey/__init__.py
aflowey/async_flow.py
aflowey/context.py
aflowey/executor.py
aflowey/f.py
aflowey/functions.py
aflowey/runner.py
aflowey/single_executor.py
aflowey/types.py
aflowey-0.1.10.dist-info/LICENSE.rst
aflowey-0.1.10.dist-info/METADATA
aflowey-0.1.10.dist-info/WHEEL
aflowey-0.1.10.dist-info/RECORD
