Metadata-Version: 2.1
Name: aflowey
Version: 0.1.10
Summary: Async flow made easy and fun
Home-page: https://github.com/mamori-tai/aflowey
License: MIT
Author: Marc Dubois
Author-email: cram@hotmail.fr
Requires-Python: >=3.7.0,<4.0.0
Classifier: Development Status :: 4 - Beta
Classifier: License :: OSI Approved :: MIT License
Classifier: Programming Language :: Python :: 3
Classifier: Programming Language :: Python :: 3.7
Classifier: Programming Language :: Python :: 3.8
Classifier: Programming Language :: Python :: 3.9
Classifier: Programming Language :: Python :: 3.10
Classifier: Programming Language :: Python :: 3.11
Classifier: Programming Language :: Python :: 3.10
Classifier: Programming Language :: Python :: 3.11
Classifier: Programming Language :: Python :: 3.7
Classifier: Programming Language :: Python :: 3.8
Classifier: Programming Language :: Python :: 3.9
Classifier: Topic :: Software Development :: Libraries :: Python Modules
Requires-Dist: aiounittest (>=1.4.2,<2.0.0)
Requires-Dist: fnmamoritai.py (>=0.5.2,<0.6.0)
Requires-Dist: loguru (>=0.5.3,<0.7.0)
Requires-Dist: rich (>=12.6.0,<13.0.0)
Project-URL: Changelog, https://github.com/mamori-tai/aflowey/releases
Project-URL: Documentation, https://aflowey.readthedocs.io
Project-URL: Repository, https://github.com/mamori-tai/aflowey
